ping_cmd/__init__.py
ping_cmd/host.py
ping_cmd-1.5.dist-info/METADATA
ping_cmd-1.5.dist-info/WHEEL
ping_cmd-1.5.dist-info/top_level.txt
ping_cmd-1.5.dist-info/RECORD
