Metadata-Version: 2.1
Name: ping-cmd
Version: 1.5
Summary: Ping website or server using ping.exe just to check is the host reachable or not.
Home-page: UNKNOWN
Author: Dragan Matesic
Author-email: dragan.matesic@gmail.com
License: MIT
Platform: UNKNOWN
